exasol/pytest_itde/__init__.py
exasol/pytest_itde/config.py
exasol/pytest_itde/version.py
pytest_exasol_itde-0.2.1.dist-info/METADATA
pytest_exasol_itde-0.2.1.dist-info/WHEEL
pytest_exasol_itde-0.2.1.dist-info/entry_points.txt
pytest_exasol_itde-0.2.1.dist-info/RECORD
