Metadata-Version: 2.1
Name: pytest-exasol-itde
Version: 0.2.1
Summary: 
Author: Nicola Coretti
Author-email: nicola.coretti@exasol.com
Requires-Python: >=3.8,<4
Classifier: Programming Language :: Python :: 3
Classifier: Programming Language :: Python :: 3.8
Classifier: Programming Language :: Python :: 3.9
Classifier: Programming Language :: Python :: 3.10
Classifier: Programming Language :: Python :: 3.11
Classifier: Programming Language :: Python :: 3.12
Requires-Dist: exasol-integration-test-docker-environment (>=3.1.0,<4.0.0)
Requires-Dist: pyexasol (>=0.25,<1)
Requires-Dist: pytest (>=7,<9)
